{
  "properties": [
    {
      "propertyName": "estado",
      "value": "todo",
      "displayName": "Estado: Todo",
      "keyBinding": "Alt+1",
      "propertyType": "list",
      "allowMultipleValues": false
    },
    {
      "propertyName": "estado",
      "value": "doing",
      "displayName": "Estado: Doing",
      "keyBinding": "Alt+2",
      "propertyType": "list",
      "allowMultipleValues": false
    },
    {
      "propertyName": "estado",
      "value": "done",
      "displayName": "Estado: Done",
      "keyBinding": "Alt+3",
      "propertyType": "list",
      "allowMultipleValues": false
    },
    {
      "propertyName": "estado",
      "value": "planned",
      "displayName": "Estado: Planned",
      "keyBinding": "Alt+4",
      "propertyType": "list",
      "allowMultipleValues": false
    },
    {
      "propertyName": "tags",
      "value": "inbox",
      "displayName": "Tags: Inbox",
      "keyBinding": "Alt+z",
      "propertyType": "list",
      "allowMultipleValues": false
    }
  ],
  "version": 3,
  "commandVersion": 20
}